karton_archive_extractor-1.5.0-nspkg.pth
karton/archive_extractor/__init__.py
karton/archive_extractor/__main__.py
karton/archive_extractor/__version__.py
karton/archive_extractor/archive_extractor.py
karton/archive_extractor/unpacker.py
karton_archive_extractor-1.5.0.dist-info/LICENSE
karton_archive_extractor-1.5.0.dist-info/METADATA
karton_archive_extractor-1.5.0.dist-info/WHEEL
karton_archive_extractor-1.5.0.dist-info/entry_points.txt
karton_archive_extractor-1.5.0.dist-info/namespace_packages.txt
karton_archive_extractor-1.5.0.dist-info/top_level.txt
karton_archive_extractor-1.5.0.dist-info/RECORD
