Metadata-Version: 2.1
Name: karton-archive-extractor
Version: 1.5.0
Summary: Extractor of various archive formats for Karton framework
Home-page: https://github.com/CERT-Polska/karton-archive-extractor/
Classifier: Programming Language :: Python
Classifier: Operating System :: OS Independent
Requires-Python: >=3.10
License-File: LICENSE
Requires-Dist: SFlock2[linux] ==0.3.80
Requires-Dist: karton-core <6.0.0,>=5.0.0
Provides-Extra: debloat
Requires-Dist: debloat ==1.6.5 ; extra == 'debloat'
Requires-Dist: pefile ; extra == 'debloat'
